Workbook

Sheet ลิสต์รายการโอนงิน
A1: รายการโอนรายวัน Bualuang Mbanking | M1: สำรองเจ้าหน้าที่ | N1: รายเดือนปราบปรามภาค8 11/68 - 4/69 | O1: ปป. ภาค8 | P1: รอโกจุ่งแจ้งเลขที่บัญชีมาใหม่คะ | R1: รายการโอน Bualuang Mbanking
A2: ประจำเดือน พฤษภาคม 2569 (5/2026) | R2: =A2 -> ประจำเดือน พฤษภาคม 2569 (5/2026)
A3: Voucher | B3: Pst | C3: วันที่ | D3: A/Cย่อย | E3: ชื่อบัญชี | F3: รายละเอียด | G3: จ่ายให้ | H3: BY | I3: รับ | J3: จ่าย | K3: คงเหลือ | L3: หมายเหตุ | R3: ลำดับ | S3: รายการเบิกM-banking | T3: ยอดเงิน | V3: ลำดับ | W3: รายการเบิกM-banking | X3: ยอดเงิน | Z3: ลำดับ | AA3: รายการเบิกM-banking | AB3: ยอดเงิน | AD3: ลำดับ | AE3: ป้ายชื่อแถว | AF3: ผลรวม ของ จ่าย | AH3: DATA
C4: ยกมา | K4: 3587191.6 | R4: 1 | S4: กรรมการ | T4: 3763616.7 | V4: ยอดยกมา | X4: =T17 -> 11619301 | Z4: ยอดยกมา | AB4: =X21 -> 11619301 | AD4: 1 | AE4: CH-Exp | AF4: 456647.66 | AH4: BBL
A5: M69-05-001 | C5: 46143 | E5: Yส่วนตัว | F5: โอนเงินให้มะโถ้ย 5.) | G5: แฟนโกหย่ง | H5: =VLOOKUP(G5,บัญชีโอน!$B:$D,3,FALSE) -> BBL | J5: 150000 | K5: =K4+I5-J5 -> 3437191.6 | R5: 2 | S5: ร้านค้า | T5: 2605961 | V5: 28 | Z5: 14 | AA5: คานเรือโกตา | AB5: 133900 | AD5: 2 | AE5: EXP C-PAC | AF5: 25000 | AH5: SCB
A6: M69-05-002 | C6: 46143 | E6: โกต้งส่วนตัว | F6: ให้จี้เกี่ยใช้ 5.) (ปิดอ่าว#2) | G6: จี้เมธ์ | H6: =VLOOKUP(G6,บัญชีโอน!$B:$D,3,FALSE) -> TTB | J6: 100000 | K6: =K5+I6-J6 -> 3337191.6 | R6: 3 | S6: โรงงานมะริด | T6: 1449734 | V6: 29 | Z6: 15 | AA6: สำรองโกจุ่ง | AB6: 115707 | AD6: 3 | AE6: Exp M-SHOP | AF6: 56910 | AH6: Kbank
A7: M69-05-003 | C7: 46143 | E7: โกเจี้ยวส่วนตัว | F7: เงินเดือนโกเจี้ยวและครอบครัว 5.) | H7: =VLOOKUP(G7,บัญชีโอน!$B:$D,3,FALSE) -> #N/A | J7: 495000 | K7: =K6+I7-J7 -> 2842191.6 | R7: 4 | S7: HHT ICE-3 | T7: 766950 | V7: 30 | Z7: 16 | AA7: HHT ICE | AB7: 25625 | AD7: 4 | AE7: Exp MYEIK | AF7: 10500 | AH7: KTB
A8: M69-05-004 | C8: 46143 | E8: CH-Exp | F8: รายเดือนครอบครัวโกช่อง 5.) | H8: =VLOOKUP(G8,บัญชีโอน!$B:$D,3,FALSE) -> #N/A | J8: 250000 | K8: =K7+I8-J8 -> 2592191.6 | R8: 5 | S8: ค่าปลาเรือนอก | T8: 600091 | V8: 31 | Z8: 17 | AA8: EXP C-PAC | AB8: 25000 | AD8: 5 | AE8: FM | AF8: 176901 | AH8: TTB
A9: M69-05-005 | C9: 46143 | E9: สำรองเจ้าหน้าที่ | F9: รายเดือนสรรพสามิต 5.) | G9: สรรพสามิต | H9: =VLOOKUP(G9,บัญชีโอน!$B:$D,3,FALSE) -> KTB | J9: 5000 | K9: =K8+I9-J9 -> 2587191.6 | R9: 6 | S9: KPS-ห้องเย็น | T9: 600000 | V9: 32 | Z9: 18 | AA9: แพกลุ่มเกษตร | AB9: 23862 | AD9: 6 | AE9: HHT ICE | AF9: 25625 | AH9: ออมสิน
A10: M69-05-006 | C10: 46143 | E10: OFF | F10: เงินเดือนน้องอร(ชมรมแพปลา) 4.) | G10: โกจุ่ง | H10: =VLOOKUP(G10,บัญชีโอน!$B:$D,3,FALSE) -> BBL | J10: 2500 | K10: =K9+I10-J10 -> 2584691.6 | R10: 7 | S10: โกโรจน์(ถัง) | T10: 534600 | V10: 33 | Z10: 19 | AA10: YNTZ ICE | AB10: 11556 | AD10: 7 | AE10: HHT ICE-3 | AF10: 766950 | AH10: กรุงศรี
A11: M69-05-007 | C11: 46146 | E11: Exp MYEIK | F11: โอนเงิน (โกหย่งแจ้งให้โอน) | G11: MS.ZIN THU HAN | H11: =VLOOKUP(G11,บัญชีโอน!$B:$D,3,FALSE) -> P-Pay | J11: 4000 | K11: =K10+I11-J11 -> 2580691.6 | M11: =C9 -> 46143 | N11: รับ | O11: จ่าย | P11: คงเหลือ(2ลบ.) | Q11: 1 | R11: 8 | S11: สำรองเจ้าหน้าที่ | T11: 308972 | V11: 34 | Z11: 20 | AA11: Exp MYEIK | AB11: 10500 | AD11: 8 | AE11: ICE KAWTHAUNG | AF11: 11820 | AH11: P-pay
A12: M69-05-008 | C12: 46146 | E12: Exp MYEIK | F12: ค่ารถและค่าไกด์ (โกหย่งแจ้งให้โอน) | G12: ยี่เอ้ง | H12: =VLOOKUP(G12,บัญชีโอน!$B:$D,3,FALSE) -> BBL | J12: 6500 | K12: =K11+I12-J12 -> 2574191.6 | M12: รวมสุทธิ | N12: =SUM(I4:I12) -> 0 | O12: =SUM(J4:J12) -> 1013000 | P12: =2000000-O12 -> 987000 | R12: 9 | S12: เรือปั่นไฟ HHT-12 | T12: 270500 | V12: 35 | Z12: 21 | AA12: รถน้ำ | AB12: 10102 | AD12: 9 | AE12: Ko Than Win(z) | AF12: 200000 | AH12: TRUE
A13: M69-05-009 | C13: 46147 | E13: ต้นน้ำจืด | F13: ค่าน้ำจืด 4.) (128คันx140 ) | G13: ต้นน้ำจืด | H13: =VLOOKUP(G13,บัญชีโอน!$B:$D,3,FALSE) -> KTB | J13: 17920 | K13: =K12+I13-J13 -> 2556271.6 | R13: 10 | S13: จี้หม่วย | T13: 200569 | V13: 36 | Z13: 22 | AA13: เรือภายใน | AB13: 6754 | AD13: 10 | AE13: KPS-ท่าเรือเขานางหงส์ | AF13: 78360 | AH13: QR CODE
A14: M69-05-010 | C14: 46147 | E14: บ่อน้ำตาอิน | F14: ค่าน้ำจืด 4.) (48คันx150 ) | G14: บ่อน้ำตาอิน | H14: =VLOOKUP(G14,บัญชีโอน!$B:$D,3,FALSE) -> TTB | J14: 7200 | K14: =K13+I14-J14 -> 2549071.6 | R14: 11 | S14: Ko Than Win(z) | T14: 200000 | V14: 37 | Z14: 23 | AA14: OFF | AB14: 3568.93 | AD14: 11 | AE14: KPS-ห้องเย็น | AF14: 600000
A15: M69-05-011 | C15: 46147 | E15: สำรองทิพย์ | F15: ค่าโทรศัพท์AIS 4.) | G15: ทิพย์ (ท่าเรือฯ)2 | H15: =VLOOKUP(G15,บัญชีโอน!$B:$D,3,FALSE) -> P-Pay | J15: 6754 | K15: =K14+I15-J15 -> 2542317.6 | R15: 12 | S15: FM | T15: 176901 | V15: 38 | Z15: 24 | AA15: YNTZ CONCRETE ทำงาน | AB15: 2247 | AD15: 12 | AE15: KSส่วนตัว (โกตาต้า) | AF15: 1000000 | AH15: ค่าปลาเรือนอก
A16: M69-05-012 | C16: 46147 | E16: ชาญสยามขนส่ง | F16: ค่าบรรทุกปลาป่นRGT#15/25-26 WTK (14คัน)(หักW/Tax 1,330.-) รอบที่ 1 | G16: ชาญสยามขนส่ง | H16: =VLOOKUP(G16,บัญชีโอน!$B:$D,3,FALSE) -> Kbank | J16: 131670 | K16: =K15+I16-J16 -> 2410647.6 | R16: 13 | S16: PT(1) | T16: 141406 | V16: 39 | Z16: 25 | AA16: ค่าใช้จ่ายเรือบาร์ช | AB16: 2140 | AD16: 13 | AE16: M-SHOP | AF16: 1367824 | AH16: KWB-Exp
A17: M69-05-013 | C17: 46147 | E17: สำรองโกจุ่ง | F17: ค่าเช่าธนสาร2/ใต้โต๊ะ/ตม. 4.) | G17: โกจุ่ง | H17: =VLOOKUP(G17,บัญชีโอน!$B:$D,3,FALSE) -> BBL | J17: 115707 | K17: =K16+I17-J17 -> 2294940.6 | R17: ยอดยกไป | T17: =SUM(T4:T16) -> 11619301 | V17: 50 | Z17: รวมรายการโอนMbanking | AB17: =SUM(AB4:AB16) -> 11990263 | AD17: 14 | AE17: MV.001 | AF17: 2140 | AH17: LB
A18: M69-05-014 | C18: 46147 | E18: โกต้งส่วนตัว | F18: ค่าของ 3.) (บ้านโกต้ง) | G18: มงคลพรหมระนอง | H18: =VLOOKUP(G18,บัญชีโอน!$B:$D,3,FALSE) -> อิสลาม | J18: 5450 | K18: =K17+I18-J18 -> 2289490.6 | V18: 51 | AD18: 15 | AE18: OFF | AF18: 3568.93 | AH18: TTL-59
A19: M69-05-015 | C19: 46147 | E19: M-SHOP | F19: ลวดเชื่อม | G19: THAI KOBELCO WELDING | H19: =VLOOKUP(G19,บัญชีโอน!$B:$D,3,FALSE) -> MIZUHO | J19: 379368 | K19: =K18+I19-J19 -> 1910122.6 | V19: 52 | AA19: ยอดยกมาจาก ก.พ.69 | AB19: =K4 -> 3587191.6 | AD19: 16 | AE19: PJ | AF19: 10480 | AH19: TS
A20: M69-05-016 | C20: 46147 | E20: บจ.โรงกลึงสองวัลย์ | F20: มัดจำ50% หน้าต่าง,ลูกบิด,ยางฟองน้ำ | G20: บจ.โรงกลึงสองวัลย์ | H20: =VLOOKUP(G20,บัญชีโอน!$B:$D,3,FALSE) -> Kbank | J20: 390300 | K20: =K19+I20-J20 -> 1519822.6 | V20: 53 | AA20: บวก นำเงินเข้าบัญชี | AB20: =I224 -> 12480724 | AD20: 17 | AE20: PT(1) | AF20: 141406 | AH20: U SOE THEIN | AI20: 600091
A21: M69-05-017 | C21: 46147 | E21: M-SHOP | F21: ทางแยกน้ำทองเหลือง(5ชิ้น) | G21: บจ.ยนตรการเมทัลเวิร์ค | H21: =VLOOKUP(G21,บัญชีโอน!$B:$D,3,FALSE) -> BBL | J21: 15789 | K21: =K20+I21-J21 -> 1504033.6 | V21: ยอดยกไป | X21: =SUM(X4:X20) -> 11619301 | AA21: หัก รายการเบิก | AB21: =-AB17 -> -11990263 | AD21: 18 | AE21: TK-โรงกลึง | AF21: 661712 | AH21: แพโกศิษย์-ขายปลา
A22: M69-05-018 | C22: 46147 | E22: M-SHOP | F22: ตะปูตะกั่ว 40กก. | G22: บจ.แกรนเมโทรฮาร์ดแวร์ | H22: =VLOOKUP(G22,บัญชีโอน!$B:$D,3,FALSE) -> Kbank | J22: 5800 | K22: =K21+I22-J22 -> 1498233.6 | M22: =C13 -> 46147 | N22: รับ | O22: จ่าย | P22: คงเหลือ(2ลบ.) | Q22: 2 | AA22: ยอดคงเหลือสุทธิ | AB22: =SUM(AB19:AB21) -> 4077653 | AC22: =K223-AB22 -> 0 | AD22: 19 | AE22: U SOE THEIN (YST) | AF22: 600091 | AH22: ช่างเพชร*ขายปลา
A23: M69-05-019 | C23: 46147 | E23: FM | F23: ค่าวิเคราะห์ปลาป่น #15/25-26 WTK (54x710.-) | G23: บจ.จรมิตร | H23: =VLOOKUP(G23,บัญชีโอน!$B:$D,3,FALSE) -> Kbank | J23: 38340 | K23: =K22+I23-J23 -> 1459893.6 | M23: รวมสุทธิ | N23: =SUM(I13:I23) -> 0 | O23: =SUM(J13:J23) -> 1114298 | P23: =2000000-O23 -> 885702 | AD23: 20 | AE23: UTK เรือรวม | AF23: 45000 | AH23: ย้อล่วย
C24: 46148 | E24: BBL 966-1 | F24: นำเงินเข้าบัญชี | H24: =VLOOKUP(G24,บัญชีโอน!$B:$D,3,FALSE) -> #N/A | I24: 3000000 | K24: =K23+I24-J24 -> 4459893.6 | AD24: 21 | AE24: YNTZ CONCRETE ทำงาน | AF24: 2247 | AH24: โกเซ็ก
A25: M69-05-020 | C25: 46148 | E25: ชาญสยามขนส่ง | F25: ค่าบรรทุกปลาป่นRGT#15/25-26 WTK (8คัน)(หักW/Tax 760.-) รอบที่ 2 | G25: ชาญสยามขนส่ง | H25: =VLOOKUP(G25,บัญชีโอน!$B:$D,3,FALSE) -> Kbank | J25: 75240 | K25: =K24+I25-J25 -> 4384653.6 | AD25: 22 | AE25: YNTZ C-PAC | AF25: 25000 | AH25: สำรองเรือUTK
A26: M69-05-021 | C26: 46148 | E26: โกชุ้น (ขนส่ง) | F26: ค่าบรรทุกปลาป่นRGT#15/25-26 WTK (6คัน)(หักW/Tax 570.-) | G26: โกชุ้น (ขนส่ง) | H26: =VLOOKUP(G26,บัญชีโอน!$B:$D,3,FALSE) -> Kbank | J26: 56430 | K26: =K25+I26-J26 -> 4328223.6 | AD26: 23 | AE26: YNTZ ICE | AF26: 11556 | AH26: ค่าปลาเรือนอก | AI26: =SUM(AI16:AI25) -> 600091
A27: M69-05-022 | C27: 46148 | E27: ตันเก้ง | F27: ค่าบรรทุกปลาป่นRGT#15/25-26 WTK (4คัน)(หักW/Tax 380.-) | G27: บจ.ทีเค.วัน ขนส่ง และ เซอร์วิส | H27: =VLOOKUP(G27,บัญชีโอน!$B:$D,3,FALSE) -> BBL | J27: 37620 | K27: =K26+I27-J27 -> 4290603.6 | AD27: 24 | AE27: Yส่วนตัว | AF27: 320000
A28: M69-05-023 | C28: 46148 | E28: ตั้งข้าวสาร | F28: ค่าบรรทุกปลาป่นRGT#15/25-26 WTK (4คัน)(หักW/Tax 380.-) | G28: ตั้งข้าวสาร | H28: =VLOOKUP(G28,บัญชีโอน!$B:$D,3,FALSE) -> Kbank | J28: 37620 | K28: =K27+I28-J28 -> 4252983.6 | AD28: 25 | AE28: กิจไพศาลวัสดุ | AF28: 23452 | AH28: อวนดำ
A29: M69-05-024 | C29: 46148 | E29: หจก.เสกศิริเนติพันธ์ | F29: ค่าบรรทุกปลาป่นRGT#15/25-26 WTK (4คัน)(หักW/Tax 380.-) | G29: หจก.เสกศิริเนติพันธ์ | H29: =VLOOKUP(G29,บัญชีโอน!$B:$D,3,FALSE) -> Kbank | J29: 37620 | K29: =K28+I29-J29 -> 4215363.6 | AD29: 26 | AE29: โกเจี้ยวส่วนตัว | AF29: 495000 | AH29: ค่าทัวร์อวนดำ
A30: M69-05-025 | C30: 46148 | E30: พรรณแก้ว(ขนส่ง) | F30: ค่าบรรทุกปลาป่นRGT#15/25-26 WTK (2คัน)(หักW/Tax 190.-) | G30: บจ.พรรณแก้วขนส่ง | H30: =VLOOKUP(G30,บัญชีโอน!$B:$D,3,FALSE) -> Kbank | J30: 18810 | K30: =K29+I30-J30 -> 4196553.6 | AD30: 27 | AE30: โกชุ้น (ขนส่ง) | AF30: 56430 | AH30: HHT-12
A31: M69-05-026 | C31: 46148 | E31: วาสนาอดิศรขนส่ง | F31: ค่าบรรทุกปลาป่นRGT#15/25-26 WTK (2คัน)(หักW/Tax 190.-) | G31: วาสนาอดิศร | H31: =VLOOKUP(G31,บัญชีโอน!$B:$D,3,FALSE) -> TTB | J31: 18810 | K31: =K30+I31-J31 -> 4177743.6 | AD31: 28 | AE31: โกต้งส่วนตัว | AF31: 680077 | AH31: HHT-15
A32: M69-05-027 | C32: 46148 | E32: แร่นอง(ขนส่ง) | F32: ค่าบรรทุกปลาป่นRGT#15/25-26 WTK (2คัน)(หักW/Tax 190.-) | G32: แร่นอง(ขนส่ง) | H32: =VLOOKUP(G32,บัญชีโอน!$B:$D,3,FALSE) -> SCB | J32: 18810 | K32: =K31+I32-J32 -> 4158933.6 | AD32: 29 | AE32: โกโรจน์(ถัง) | AF32: 534600 | AH32: HHT-19
A33: M69-05-028 | C33: 46148 | E33: พี่ธงชัย | F33: ค่าบรรทุกปลาป่นRGT#15/25-26 WTK (2คัน)(หักW/Tax 190.-) | G33: พี่ธงชัย | H33: =VLOOKUP(G33,บัญชีโอน!$B:$D,3,FALSE) -> Kbank | J33: 18810 | K33: =K32+I33-J33 -> 4140123.6 | AD33: 30 | AE33: คานเรือโกตา | AF33: 133900 | AH33: UTK-27
A34: M69-05-029 | C34: 46148 | E34: อันดามันขนส่ง(โกกิ้ว) | F34: ค่าบรรทุกปลาป่นRGT#15/25-26 WTK (2คัน)(หักW/Tax 190.-) | G34: อันดามันขนส่ง(โกกิ้ว) | H34: =VLOOKUP(G34,บัญชีโอน!$B:$D,3,FALSE) -> TTB | J34: 18810 | K34: =K33+I34-J34 -> 4121313.6 | M34: =C34 -> 46148 | N34: รับ | O34: จ่าย | P34: คงเหลือ(2ลบ.) | Q34: 3 | AD34: 31 | AE34: ค่าผ่านแพกิจไพศาล | AF34: 15000 | AH34: UTK-54
A35: M69-05-030 | C35: 46148 | E35: หจก.เอส.เอ็ม.พี ระนองเทรดดิ้ง | F35: ค่าบรรทุกปลาป่นRGT#15/25-26 WTK (4คัน)(หักW/Tax 380.-) | G35: หจก.เอส.เอ็ม.พี ระนองเทรดดิ้ง | H35: =VLOOKUP(G35,บัญชีโอน!$B:$D,3,FALSE) -> KTB | J35: 37620 | K35: =K34+I35-J35 -> 4083693.6 | M35: รวมสุทธิ | N35: =SUM(I24:I35) -> 3000000 | O35: =SUM(J24:J35) -> 376200 | P35: =2000000-O35 -> 1623800 | AD35: 32 | AE35: จี้หม่วย | AF35: 200569 | AH35: UTK-63
A36: 035/1738 | C36: 46149 | E36: HHT-S | F36: รับค่าของ | H36: =VLOOKUP(G36,บัญชีโอน!$B:$D,3,FALSE) -> #N/A | I36: 143040 | K36: =K35+I36-J36 -> 4226733.6 | AD36: 33 | AE36: ชัยวัฒน์การช่าง | AF36: 121795 | AH36: MIN OO บ/ช.รวมค่าทัวร์อวนดำ
A37: M69-05-031 | C37: 46149 | E37: โกต้งส่วนตัว | F37: ค่าของ 4.) (อาหารไก่, ตาข่ายกรองแสง,สปริงฯ) | G37: บจ.มานิตย์ระนองการเกษตร | H37: =VLOOKUP(G37,บัญชีโอน!$B:$D,3,FALSE) -> SCB | J37: 4950 | K37: =K36+I37-J37 -> 4221783.6 | AD37: 34 | AE37: ช่างเดช-ต่อเรือเหล็ก(พ่นทราย) | AF37: 792000 | AH37: อวนดำ | AI37: =SUM(AI29:AI36) -> 0
A38: M69-05-032 | C38: 46149 | E38: KSส่วนตัว (โกตาต้า) | F38: เบิกเงิน | G38: MR.ZAW MYO TUN | H38: =VLOOKUP(G38,บัญชีโอน!$B:$D,3,FALSE) -> BBL | J38: 500000 | K38: =K37+I38-J38 -> 3721783.6 | AD38: 35 | AE38: ช่างพร | AF38: 60000
A39: M69-05-033 | C39: 46149 | E39: TK-โรงกลึง | F39: ค่าซ่อมและค่าอะไหล่,เงินทุนค่าอะไหล่ฯ 4.) | G39: โกแดง | H39: =VLOOKUP(G39,บัญชีโอน!$B:$D,3,FALSE) -> KTB | J39: 661712 | K39: =K38+I39-J39 -> 3060071.6 | AD39: 36 | AE39: ช่างเยื้อน | AF39: 52500 | AH39: เรือภายใน
A40: M69-05-034 | C40: 46149 | E40: HHT ICE-3 | F40: น้ำยาโฟม 5,053กก. | G40: นายสมบูรณ์ พงษ์ขยัน | H40: =VLOOKUP(G40,บัญชีโอน!$B:$D,3,FALSE) -> Kbank | J40: 757950 | K40: =K39+I40-J40 -> 2302121.6 | M40: =C36 -> 46149 | N40: รับ | O40: จ่าย | P40: คงเหลือ(2ลบ.) | Q40: 4 | AD40: 37 | AE40: ชาญสยามขนส่ง | AF40: 206910 | AH40: สำรองทิพย์ | AI40: 6754
A41: M69-05-035 | C41: 46149 | E41: อู่ช่างปลา | F41: ค่าซ่อมช่วงล่าง บง6505 | G41: อู่ช่างปลา | H41: =VLOOKUP(G41,บัญชีโอน!$B:$D,3,FALSE) -> TTB | J41: 3850 | K41: =K40+I41-J41 -> 2298271.6 | M41: รวมสุทธิ | N41: =SUM(I36:I41) -> 143040 | O41: =SUM(J36:J41) -> 1928462 | P41: =2000000-O41 -> 71538 | AD41: 38 | AE41: ต้นน้ำจืด | AF41: 17920
A42: M69-05-036 | C42: 46150 | E42: อู่ช่างปลา | F42: ค่าแรงและค่าของซ่อมบันไดฯ 80-5271 | G42: อู่ช่างปลา | H42: =VLOOKUP(G42,บัญชีโอน!$B:$D,3,FALSE) -> TTB | J42: 13440 | K42: =K41+I42-J42 -> 2284831.6 | AD42: 39 | AE42: ตั้งข้าวสาร | AF42: 37620 | AH42: เรือภายใน | AI42: =SUM(AI40:AI41) -> 6754
A43: M69-05-037 | C43: 46150 | E43: KPS-ห้องเย็น | F43: เบิกเงินสดย่อย | G43: พี่เสง(KPS-ห้องเย็น) | H43: =VLOOKUP(G43,บัญชีโอน!$B:$D,3,FALSE) -> Kbank | J43: 200000 | K43: =K42+I43-J43 -> 2084831.6 | M43: =C42 -> 46150 | N43: รับ | O43: จ่าย | P43: คงเหลือ(2ลบ.) | Q43: 5 | AD43: 40 | AE43: ตันเก้ง | AF43: 37620
A44: M69-05-038 | C44: 46150 | E44: ICE KAWTHAUNG | F44: ค่าแรงซ่อมสปีดคอนโทรล+ค่าเรือ | G44: ช่างหมู | H44: =VLOOKUP(G44,บัญชีโอน!$B:$D,3,FALSE) -> Kbank | J44: 7500 | K44: =K43+I44-J44 -> 2077331.6 | M44: รวมสุทธิ | N44: =SUM(I42:I44) -> 0 | O44: =SUM(J42:J44) -> 220940 | P44: =2000000-O44 -> 1779060 | AD44: 41 | AE44: นพดลการไฟฟ้า | AF44: 14700
A45: M69-05-039 | C45: 46153 | E45: โรงน้ำแข็งเจริญชัย | F45: ค่าน้ำแข็งดองปลา 4.) | G45: คุณเล็ก(ค่าน้ำแข็ง) | H45: =VLOOKUP(G45,บัญชีโอน!$B:$D,3,FALSE) -> SCB | J45: 9025 | K45: =K44+I45-J45 -> 2068306.6 | AD45: 42 | AE45: บจ.โรงกลึงสองวัลย์ | AF45: 390300
A46: M69-05-040 | C46: 46153 | E46: โรงน้ำแข็งเจริญชัย | F46: ค่าน้ำแข็ง 4.) (30ซองx100) (วาสนาอดิศร) | G46: คุณเล็ก(ค่าน้ำแข็ง) | H46: =VLOOKUP(G46,บัญชีโอน!$B:$D,3,FALSE) -> SCB | J46: 3000 | K46: =K45+I46-J46 -> 2065306.6 | AD46: 43 | AE46: บ่อน้ำตาอิน | AF46: 7200 | AH46: โรงงานมะริด
A47: M69-05-041 | C47: 46153 | E47: ระนองลิเดอร์ | F47: ค่าเครื่องดื่ม 4.) | G47: ระนองลิเดอร์ | H47: =VLOOKUP(G47,บัญชีโอน!$B:$D,3,FALSE) -> BAY | J47: 9370 | K47: =K46+I47-J47 -> 2055936.6 | AD47: 44 | AE47: ปั้มตันปุ้น | AF47: 41370 | AH47: Exp M-SHOP | AI47: 56910
A48: M69-05-042 | C48: 46153 | E48: อู่ขวัญชีวิต | F48: ค่าซ่อมรถ 4.) | G48: อู่ขวัญชีวิต | H48: =VLOOKUP(G48,บัญชีโอน!$B:$D,3,FALSE) -> SCB | J48: 46450 | K48: =K47+I48-J48 -> 2009486.6 | AD48: 45 | AE48: พ.เจริญยนต์ | AF48: 21721 | AH48: M-SHOP | AI48: 1367824
A49: M69-05-043 | C49: 46153 | E49: อันดามันขนส่ง(โกกิ้ว) | F49: ค่าบรรทุกของ 4.) | G49: อันดามันขนส่ง(โกกิ้ว) | H49: =VLOOKUP(G49,บัญชีโอน!$B:$D,3,FALSE) -> TTB | J49: 2790 | K49: =K48+I49-J49 -> 2006696.6 | AD49: 46 | AE49: พรรณแก้ว(ขนส่ง) | AF49: 18810 | AH49: YNTZ CPAC | AI49: 25000
A50: M69-05-044 | C50: 46153 | E50: นพดลการไฟฟ้า | F50: ค่าแรง 4.) | G50: นพดลการไฟฟ้า | H50: =VLOOKUP(G50,บัญชีโอน!$B:$D,3,FALSE) -> SCB | J50: 14700 | K50: =K49+I50-J50 -> 1991996.6 | AD50: 47 | AE50: พี่ธงชัย | AF50: 18810 | AH50: ช่างแมว
A51: M69-05-045 | C51: 46153 | E51: PJ | F51: ค่าวัสดุและอุปกรณ์อื่นๆ 4.) | G51: PJ | H51: =VLOOKUP(G51,บัญชีโอน!$B:$D,3,FALSE) -> Kbank | J51: 10480 | K51: =K50+I51-J51 -> 1981516.6 | AD51: 48 | AE51: พี่สาโรจน์ | AF51: 175050 | AH51: โรงงานมะริด | AI51: =SUM(AI47:AI50) -> 1449734
A52: M69-05-046 | C52: 46153 | E52: มุกอะไหล่ | F52: ค่าแรงและค่าของ 4.) | G52: มุกอะไหล่ | H52: =VLOOKUP(G52,บัญชีโอน!$B:$D,3,FALSE) -> SCB | J52: 12800 | K52: =K51+I52-J52 -> 1968716.6 | AD52: 49 | AE52: แพกลุ่มเกษตร | AF52: 23862
A53: M69-05-047 | C53: 46153 | E53: ปั้มตันปุ้น | F53: ค่าน้ำมันดีเซล 4.) (รถน้ำ) | G53: ปั้มตันปุ้น. | H53: =VLOOKUP(G53,บัญชีโอน!$B:$D,3,FALSE) -> Kbank | J53: 41370 | K53: =K52+I53-J53 -> 1927346.6 | AD53: 50 | AE53: มุกอะไหล่ | AF53: 12800
A54: M69-05-048 | C54: 46153 | E54: ชัยวัฒน์การช่าง | F54: ค่าแรง 4.) | G54: ชัยวัฒน์การช่าง | H54: =VLOOKUP(G54,บัญชีโอน!$B:$D,3,FALSE) -> Kbank | J54: 121795 | K54: =K53+I54-J54 -> 1805551.6 | AD54: 51 | AE54: รถน้ำ | AF54: 10102 | AH54: กรรมการ
A55: M69-05-049 | C55: 46153 | E55: ร้านดวงดี | F55: ค่าของ 4.) | G55: ร้านดวงดี | H55: =VLOOKUP(G55,บัญชีโอน!$B:$D,3,FALSE) -> Kbank | J55: 238966 | K55: =K54+I55-J55 -> 1566585.6 | AD55: 52 | AE55: ระนองเคหะภัณฑ์ | AF55: 21412 | AH55: CH-Exp | AI55: 456647.66
A56: M69-05-050 | C56: 46153 | E56: ระนองเคหะภัณฑ์ | F56: ค่าของ 3.) - 4.) | G56: ระนองเคหะภัณฑ์ | H56: =VLOOKUP(G56,บัญชีโอน!$B:$D,3,FALSE) -> Kbank | J56: 21412 | K56: =K55+I56-J56 -> 1545173.6 | AD56: 53 | AE56: ระนองลิเดอร์ | AF56: 9370 | AH56: ICE KAWTHUANG | AI56: 11820
A57: M69-05-051 | C57: 46153 | E57: พ.เจริญยนต์ | F57: ค่าอะไหล่ซ่อมรถ 4.) | G57: พ.เจริญยนต์ | H57: =VLOOKUP(G57,บัญชีโอน!$B:$D,3,FALSE) -> BAY | J57: 21721 | K57: =K56+I57-J57 -> 1523452.6 | AD57: 54 | AE57: ร้านดวงดี | AF57: 238966 | AH57: KPS-ท่าเรือเขานางหงส์ | AI57: 78360
A58: M69-05-052 | C58: 46153 | E58: U SOE THEIN (YST) | F58: ค่าของ 4.) | G58: พรชัยอะไหล่ | H58: =VLOOKUP(G58,บัญชีโอน!$B:$D,3,FALSE) -> Kbank | J58: 600091 | K58: =K57+I58-J58 -> 923361.6 | M58: =C45 -> 46153 | N58: รับ | O58: จ่าย | P58: คงเหลือ(2ลบ.) | Q58: 6 | AD58: 55 | AE58: เรือปั่นไฟ HHT-12 | AF58: 270500 | AH58: KSส่วนตัว (โกตาต้า) | AI58: 1000000
A59: M69-05-053 | C59: 46153 | E59: โกต้งส่วนตัว | F59: ค่าเหล็ก 2.) (เขานายัง) | G59: โลหะไพโรจน์ | H59: =VLOOKUP(G59,บัญชีโอน!$B:$D,3,FALSE) -> BBL | J59: 910 | K59: =K58+I59-J59 -> 922451.6 | M59: รวมสุทธิ | N59: =SUM(I45:I59) -> 0 | O59: =SUM(J45:J59) -> 1154880 | P59: =2000000-O59 -> 845120 | AD59: 56 | AE59: แร่นอง(ขนส่ง) | AF59: 18810 | AH59: TK-โรงกลึง | AI59: 661712
C60: 46154 | E60: BBL 966-1 | F60: นำเงินเข้าบัญชี | H60: =VLOOKUP(G60,บัญชีโอน!$B:$D,3,FALSE) -> #N/A | I60: 3000000 | K60: =K59+I60-J60 -> 3922451.6 | AD60: 57 | AE60: โรงน้ำแข็งเจริญชัย | AF60: 12025 | AH60: U Kyaw Kyaw-ส่วนตัว
A61: M69-05-054 | C61: 46154 | E61: สำรองเจ้าหน้าที่ | F61: รับรองแขก (โกหย่งแจ้งให้โอนคะ) | G61: พี่เบิ้ล | H61: =VLOOKUP(G61,บัญชีโอน!$B:$D,3,FALSE) -> BBL | J61: 170000 | K61: =K60+I61-J61 -> 3752451.6 | M61: =C61 -> 46154 | N61: รับ | O61: จ่าย | P61: คงเหลือ(2ลบ.) | Q61: 7 | AD61: 58 | AE61: วาสนาอดิศรขนส่ง | AF61: 18810 | AH61: UTKเรือรวม | AI61: 45000
C62: 46154 | E62: Yส่วนตัว | F62: รับรองแขก (โกหย่งแจ้งให้โอนคะ) | G62: พี่เบิ้ล | H62: =VLOOKUP(G62,บัญชีโอน!$B:$D,3,FALSE) -> BBL | J62: 30000 | K62: =K61+I62-J62 -> 3722451.6 | M62: รวมสุทธิ | N62: =SUM(I60:I62) -> 3000000 | O62: =SUM(J60:J62) -> 200000 | P62: =2000000-O62 -> 1800000 | AD62: 59 | AE62: สำรองโกจุ่ง | AF62: 115707 | AH62: Yส่วนตัว | AI62: 320000
A63: 035/1743 | C63: 46155 | E63: ตู๋ | F63: รับค่าผ่านแพ ค่าเครน + ค่าด่านชั่ง - เงินเดือนท่าเรือ | H63: =VLOOKUP(G63,บัญชีโอน!$B:$D,3,FALSE) -> #N/A | I63: 1751101 | K63: =K62+I63-J63 -> 5473552.6 | AD63: 60 | AE63: สำรองเจ้าหน้าที่ | AF63: 308972 | AH63: Yสวนยางมะลิวัลย์
F64: - กรรมกรแทงปลาป่น - ค่าใช้จ่าย - สำรองจ่ายโกต้ง 4.) | H64: =VLOOKUP(G64,บัญชีโอน!$B:$D,3,FALSE) -> #N/A | I64: 1500000 | K64: =K63+I64-J64 -> 6973552.6 | AD64: 61 | AE64: สำรองทิพย์ | AF64: 6754 | AH64: โกเจี้ยวส่วนตัว | AI64: 495000
A65: M69-05-055 | C65: 46155 | E65: แพกลุ่มเกษตร | F65: ค่าคอนกรีต 4.) | G65: บจ.กิจไพศาลคอนกรีต | H65: =VLOOKUP(G65,บัญชีโอน!$B:$D,3,FALSE) -> TTB | J65: 23862 | K65: =K64+I65-J65 -> 6949690.6 | AD65: 62 | AE65: หจก.เสกศิริเนติพันธ์ | AF65: 37620 | AH65: โกซาฮุ่ยส่วนตัว
C66: 46155 | E66: โกต้งส่วนตัว | F66: ค่าคอนกรีต 4.) (กรีนรีไซเคิล) | G66: บจ.กิจไพศาลคอนกรีต | H66: =VLOOKUP(G66,บัญชีโอน!$B:$D,3,FALSE) -> TTB | J66: 17343 | K66: =K65+I66-J66 -> 6932347.6 | AD66: 63 | AE66: หจก.เอส.เอ็ม.พี ระนองเทรดดิ้ง | AF66: 37620 | AH66: โกต้งส่วนตัว | AI66: 680077
A67: M69-05-056 | C67: 46155 | E67: โกต้งส่วนตัว | F67: ค่าของ 4.) (ทราย,ไม้กวาดทางมะพร้าว) | G67: กิจไพศาลวัสดุ | H67: =VLOOKUP(G67,บัญชีโอน!$B:$D,3,FALSE) -> Kbank | J67: 160 | K67: =K66+I67-J67 -> 6932187.6 | AD67: 64 | AE67: อันดามันขนส่ง(โกกิ้ว) | AF67: 21600 | AH67: โกพกส่วนตัว
A68: M69-05-057 | C68: 46155 | E68: โกต้งส่วนตัว | F68: ค่าของ 4.) (เหล็ก(กล่อง+ข้ออ้อย+เส้น),ปั้มMITSU,ท่อPVC,สีฯ) | G68: บจ.กิจไพศาลวัสดุ | H68: =VLOOKUP(G68,บัญชีโอน!$B:$D,3,FALSE) -> Kbank | J68: 143692 | K68: =K67+I68-J68 -> 6788495.6 | AD68: 65 | AE68: อู่ขวัญชีวิต | AF68: 46450 | AH68: โกหัวส่วนตัว
A69: M69-05-058 | C69: 46155 | E69: M-SHOP | F69: ส่วนต่างค่าอวนดำ | G69: บจ.อวนไทย | H69: =VLOOKUP(G69,บัญชีโอน!$B:$D,3,FALSE) -> Kbank | J69: 6560 | K69: =K68+I69-J69 -> 6781935.6 | AD69: 66 | AE69: อู่ช่างปลา | AF69: 17290 | AH69: โกฮุ้ยส่วนตัว
A70: M69-05-059 | C70: 46155 | E70: MV.001 | F70: สายยก 2เส้น | G70: บจ.เลิศสยามสตีล K | H70: =VLOOKUP(G70,บัญชีโอน!$B:$D,3,FALSE) -> Kbank | J70: 2140 | K70: =K69+I70-J70 -> 6779795.6 | AD70: 67 | AE70: อู่นิพนธ์ | AF70: 8500 | AH70: ค่าผ่านแพกิจไพศาล | AI70: 15000
C71: 46155 | E71: PT(1) | F71: เหล็กแผ่น, เหล็กฉาก, ลวดเชื่อม | G71: บจ.เลิศสยามสตีล K | H71: =VLOOKUP(G71,บัญชีโอน!$B:$D,3,FALSE) -> Kbank | J71: 31811 | K71: =K70+I71-J71 -> 6747984.6 | AE71: ผลรวมทั้งหมด | AF71: 11990263 | AH71: พี่เบิ้ลส่วนตัว
A72: M69-05-060 | C72: 46155 | E72: PT(1) | F72: สีJOTUN, ทินเนอร์ | G72: หจก.เกษมพงษ์รัตน์ | H72: =VLOOKUP(G72,บัญชีโอน!$B:$D,3,FALSE) -> Kbank | J72: 20116 | K72: =K71+I72-J72 -> 6727868.6 | AH72: เรือรวมอวนลาก
A73: M69-05-061 | C73: 46155 | E73: HHT ICE-3 | F73: พลาสติกใสปูพื้น 20 ม้วน | G73: บจ.ไถ่เชียงระนอง | H73: =VLOOKUP(G73,บัญชีโอน!$B:$D,3,FALSE) -> Kbank | J73: 9000 | K73: =K72+I73-J73 -> 6718868.6 | AH73: กรรมการ | AI73: =SUM(AI55:AI72) -> 3763616.7
C74: 46155 | E74: KPS-ท่าเรือเขานางหงส์ | F74: บันไดอลูมิเนียม 8 ฟุต 1 ชิ้น | G74: บจ.ไถ่เชียงระนอง | H74: =VLOOKUP(G74,บัญชีโอน!$B:$D,3,FALSE) -> Kbank | J74: 2980 | K74: =K73+I74-J74 -> 6715888.6 | M74: =C63 -> 46155 | N74: รับ | O74: จ่าย | P74: คงเหลือ(2ลบ.) | Q74: 8
A75: M69-05-062 | C75: 46155 | E75: ICE KAWTHAUNG | F75: กาวาเนอร์คอนโทรล | G75: บจ.เจริญยนต์ไทยพัฒนา | H75: =VLOOKUP(G75,บัญชีโอน!$B:$D,3,FALSE) -> #N/A | J75: 4320 | K75: =K74+I75-J75 -> 6711568.6 | M75: รวมสุทธิ | N75: =SUM(I63:I75) -> 3251101 | O75: =SUM(J63:J75) -> 261984 | P75: =2000000-O75 -> 1738016 | AH75: ค่าใช้จ่ายเรือบาร์ช
A76: M69-05-063 | C76: 46156 | E76: CH-Exp | F76: เบิกค่าใช้จ่าย 4.) | G76: คุณเล็ก(แฟนโกช่อง) | H76: =VLOOKUP(G76,บัญชีโอน!$B:$D,3,FALSE) -> SCB | J76: 206635 | K76: =K75+I76-J76 -> 6504933.6 | AH76: ACT-18
H77: =VLOOKUP(G77,บัญชีโอน!$B:$D,3,FALSE) -> #N/A | K77: =K76+I77-J77 -> 6504933.6 | M77: =C76 -> 46156 | N77: รับ | O77: จ่าย | P77: คงเหลือ(2ลบ.) | Q77: 9 | AH77: MV-001 | AI77: 2140
H78: =VLOOKUP(G78,บัญชีโอน!$B:$D,3,FALSE) -> #N/A | K78: =K77+I78-J78 -> 6504933.6 | M78: รวมสุทธิ | N78: =SUM(I76:I78) -> 0 | O78: =SUM(J76:J78) -> 206635 | P78: =2000000-O78 -> 1793365 | AH78: PH
A79: M69-05-064 | C79: 46157 | E79: กิจไพศาลวัสดุ | F79: ค่าของ 4.) | G79: กิจไพศาลวัสดุ | H79: =VLOOKUP(G79,บัญชีโอน!$B:$D,3,FALSE) -> Kbank | J79: 15 | K79: =K78+I79-J79 -> 6504918.6 | AH79: W.P.L
A80: M69-05-065 | C80: 46157 | E80: กิจไพศาลวัสดุ | F80: ค่าของ 4.) | G80: บจ.กิจไพศาลวัสดุ | H80: =VLOOKUP(G80,บัญชีโอน!$B:$D,3,FALSE) -> Kbank | J80: 23437 | K80: =K79+I80-J80 -> 6481481.6 | AH80: W.T.K
A81: M69-05-066 | C81: 46157 | E81: UTK เรือรวม | F81: เงินเดือนช่างรวม (1-15/5/2026) | G81: ช่างรวม | H81: =VLOOKUP(G81,บัญชีโอน!$B:$D,3,FALSE) -> Kbank | J81: 22500 | K81: =K80+I81-J81 -> 6458981.6 | AH81: ค่าใช้จ่ายเรือบาร์ช | AI81: =SUM(AI76:AI80) -> 2140
A82: M69-05-067 | C82: 46157 | E82: M-SHOP | F82: สังกะสีกันกร่อน 150ก้อน | G82: บจ.พีดับบลิว อินเตอร์มาร์ท | H82: =VLOOKUP(G82,บัญชีโอน!$B:$D,3,FALSE) -> SCB | J82: 116100 | K82: =K81+I82-J82 -> 6342881.6
A83: M69-05-068 | C83: 46157 | E83: YNTZ CONCRETE ทำงาน | F83: กิ๊บดึงลวด | G83: บจ.พีอาร์วิศวกรรม K | H83: =VLOOKUP(G83,บัญชีโอน!$B:$D,3,FALSE) -> Kbank | J83: 2247 | K83: =K82+I83-J83 -> 6340634.6 | M83: =C79 -> 46157 | N83: รับ | O83: จ่าย | P83: คงเหลือ(2ลบ.) | Q83: 10 | AH83: ร้านค้า
A84: M69-05-069 | C84: 46157 | E84: โกโรจน์(ถัง) | F84: ถัง200Lit (162ใบx3,300.-) | G84: โกโรจน์ (ถัง) | H84: =VLOOKUP(G84,บัญชีโอน!$B:$D,3,FALSE) -> Kbank | J84: 534600 | K84: =K83+I84-J84 -> 5806034.6 | M84: รวมสุทธิ | N84: =SUM(I79:I84) -> 0 | O84: =SUM(J79:J84) -> 698899 | P84: =2000000-O84 -> 1301101 | AH84: PJ | AI84: 10480
A85: M69-05-070 | C85: 46160 | E85: สำรองเจ้าหน้าที่ | F85: ค่าปลา 3.)-4.) (ผู้ว่าฯ, ผู้การฯ) | G85: โกชุ้น | H85: =VLOOKUP(G85,บัญชีโอน!$B:$D,3,FALSE) -> Kbank | J85: 8972 | K85: =K84+I85-J85 -> 5797062.6 | AH85: PPไฮโดรลิค(TLไฮโดรลิค)
A86: M69-05-071 | C86: 46160 | E86: ช่างเยื้อน | F86: ค่าแรงซ่อมเรือPT-1 (หักเบิกเงินสด 30,000) | G86: ช่างเยื้อน | H86: =VLOOKUP(G86,บัญชีโอน!$B:$D,3,FALSE) -> BBL | J86: 52500 | K86: =K85+I86-J86 -> 5744562.6 | M86: =C86 -> 46160 | N86: รับ | O86: จ่าย | P86: คงเหลือ(2ลบ.) | Q86: 11 | AH86: W.S.เซอร์วิส
A87: M69-05-072 | C87: 46160 | E87: KPS-ท่าเรือเขานางหงส์ | F87: ค่าภาษี,ค่าจัดการ,ธรรมเนียม,บริการ (80-5479) | G87: น.ส.ชุฤณี เอี่ยมองค์ | H87: =VLOOKUP(G87,บัญชีโอน!$B:$D,3,FALSE) -> Kbank | J87: 6172 | K87: =K86+I87-J87 -> 5738390.6 | M87: รวมสุทธิ | N87: =SUM(I85:I87) -> 0 | O87: =SUM(J85:J87) -> 67644 | P87: =2000000-O87 -> 1932356 | AH87: ก.แสงทอง
A88: M69-05-073 | C88: 46161 | E88: CH-Exp | F88: ภาษีที่ดินและสิ่งปลูกสร้าง ปี 2569(บ้านซ.นกเขา) | G88: เทศบาลเมืองบางริ้น | H88: =VLOOKUP(G88,บัญชีโอน!$B:$D,3,FALSE) -> QRCode | J88: 12.66 | K88: =K87+I88-J88 -> 5738377.9 | AH88: กิจไพศาลวัสดุ | AI88: 23452
A89: M69-05-074 | C89: 46161 | E89: KSส่วนตัว (โกตาต้า) | F89: เบิกเงิน | G89: MS.YIN YIN HTIKE | H89: =VLOOKUP(G89,บัญชีโอน!$B:$D,3,FALSE) -> BBL | J89: 500000 | K89: =K88+I89-J89 -> 5238377.9 | AH89: โกชุ้น (ขนส่ง) | AI89: 56430
A90: M69-05-075 | C90: 46161 | E90: Ko Than Win(z) | F90: โอนเงิน (จี้แดง) (19/5) | G90: จี้เมธ์ . | H90: =VLOOKUP(G90,บัญชีโอน!$B:$D,3,FALSE) -> BBL | J90: 200000 | K90: =K89+I90-J90 -> 5038377.9 | AH90: โกพันธ์
A91: M69-05-076 | C91: 46161 | E91: Yส่วนตัว | F91: ต่อเติมบ้านชาญอิสระ งวดที่1 | G91: พี่เบิ้ล | H91: =VLOOKUP(G91,บัญชีโอน!$B:$D,3,FALSE) -> BBL | J91: 105000 | K91: =K90+I91-J91 -> 4933377.9 | AH91: โกหมกขนส่ง
A92: M69-05-077 | C92: 46161 | E92: M-SHOP | F92: ส่วนต่างเชือกใยยักษ์,อวนไนล่อน | G92: บจ.อวนไทย | H92: =VLOOKUP(G92,บัญชีโอน!$B:$D,3,FALSE) -> Kbank | J92: 8606 | K92: =K91+I92-J92 -> 4924771.9 | AH92: โกเอขนส่ง
A93: M69-05-078 | C93: 46161 | E93: YNTZ ICE | F93: อะไหล่รอก | G93: บจ.ย่งฮงประเทศไทย | H93: =VLOOKUP(G93,บัญชีโอน!$B:$D,3,FALSE) -> Kbank | J93: 11556 | K93: =K92+I93-J93 -> 4913215.9 | AH93: คอนกรีตซีแพคระนอง
A94: M69-05-079 | C94: 46161 | E94: M-SHOP | F94: บอลวาล์วหน้าแปลนสแตนเลส | G94: หจก.ฮะเซ้งพาณิชย์ | H94: =VLOOKUP(G94,บัญชีโอน!$B:$D,3,FALSE) -> Kbank | J94: 52681 | K94: =K93+I94-J94 -> 4860534.9 | AH94: คลีนิคมือถือ
A95: M69-05-080 | C95: 46161 | E95: PT(1) | F95: สีJOTUN, ทินเนอร์ | G95: หจก.เกษมพงษ์รัตน์ | H95: =VLOOKUP(G95,บัญชีโอน!$B:$D,3,FALSE) -> Kbank | J95: 83701 | K95: =K94+I95-J95 -> 4776833.9 | AH95: ชัยวัฒน์การช่าง | AI95: 121795
A96: M69-05-081 | C96: 46161 | E96: KPS-ท่าเรือเขานางหงส์ | F96: โวลีน AWE ไฮโดรลิค ออยล์ | G96: บจ.วีอาร์. วาเลอร์ | H96: =VLOOKUP(G96,บัญชีโอน!$B:$D,3,FALSE) -> BBL | J96: 13740 | K96: =K95+I96-J96 -> 4763093.9 | AH96: ชัยสิงห์ชิปปิ้ง
A97: M69-05-082 | C97: 46161 | E97: M-SHOP | F97: หลอดไฟ,ขั้วกันน้ำ ฯ | G97: บจ.เทพศิริ | H97: =VLOOKUP(G97,บัญชีโอน!$B:$D,3,FALSE) -> BBL | J97: 72900 | K97: =K96+I97-J97 -> 4690193.9 | AH97: ช่างเดช-ต่อเรือเหล็ก(พ่นทราย) | AI97: 792000
A98: M69-05-083 | C98: 46161 | E98: PT(1) | F98: แป๊ป, เพลา | G98: บจ.เลิศสยามสตีล K | H98: =VLOOKUP(G98,บัญชีโอน!$B:$D,3,FALSE) -> Kbank | J98: 5778 | K98: =K97+I98-J98 -> 4684415.9 | AH98: ช่างบ่าว
A99: M69-05-084 | C99: 46161 | E99: KPS-ห้องเย็น | F99: เบิกเงินสดย่อย | G99: พี่เสง(KPS-ห้องเย็น) | H99: =VLOOKUP(G99,บัญชีโอน!$B:$D,3,FALSE) -> Kbank | J99: 400000 | K99: =K98+I99-J99 -> 4284415.9 | AH99: ช่างบี้
A100: M69-05-085 | C100: 46161 | E100: โกต้งส่วนตัว | F100: ติดตั้งเสา,เชื่อมหลังคา,มุงหลังคา (กรีนรีไซเคิล) | G100: ช่างวี | H100: =VLOOKUP(G100,บัญชีโอน!$B:$D,3,FALSE) -> Kbank | J100: 110590 | K100: =K99+I100-J100 -> 4173825.9 | M100: =C88 -> 46161 | N100: รับ | O100: จ่าย | P100: คงเหลือ(2ลบ.) | Q100: 12 | AH100: ช่างพร | AI100: 60000
...

Sheet รายงานโอนเงินแบบรายยปี
A1: ลำดับ | B1: แผนก | C1: ชื่อบัญชี | D1: ม.ค. | E1: ก.พ. | F1: มี.ค. | G1: เม.ย. | H1: พ.ค. | I1: มิ.ย. | J1: ก.ค. | K1: ส.ค. | L1: ก.ย. | M1: ต.ค. | O1: พ.ย. | P1: ธ.ค. | Q1: รวม
A2: 1 | C2: % HHT-14 | Q2: =SUM(D2:P2) -> 0
C3: A-10 | Q3: =SUM(D3:P3) -> 0
A4: 2 | C4: A-12 | Q4: =SUM(D4:P4) -> 0
A5: 3 | C5: A-18 | Q5: =SUM(D5:P5) -> 0
C6: ABC ขายปลาอวนดำ | Q6: =SUM(D6:P6) -> 0
A7: 4 | C7: ACT.18 | Q7: =SUM(D7:P7) -> 0
C8: APS-7 | Q8: =SUM(D8:P8) -> 0
A9: 5 | C9: B-5 | Q9: =SUM(D9:P9) -> 0
A10: 6 | C10: BBL 1326-7 | Q10: =SUM(D10:P10) -> 0
A11: 7 | C11: BBL 1337-4 (KPS) | Q11: =SUM(D11:P11) -> 0
A12: 8 | C12: BBL 15850-3 (T&Y) | Q12: =SUM(D12:P12) -> 0
A13: 9 | C13: BBL 1765-6 | Q13: =SUM(D13:P13) -> 0
A14: 10 | C14: BBL 4241-4 | Q14: =SUM(D14:P14) -> 0
A15: 11 | C15: BBL 45002-5(FIX11M.) | Q15: =SUM(D15:P15) -> 0
A16: 12 | C16: BBL 5889-9 | Q16: =SUM(D16:P16) -> 0
A17: 13 | C17: BBL 7118-3(K.อดิศักดิ์) | Q17: =SUM(D17:P17) -> 0
A18: 14 | C18: BBL 9250-4(K.อดิศักดิ์&K.ธนู) | Q18: =SUM(D18:P18) -> 0
A19: 15 | C19: CD ส่วนตัว | Q19: =SUM(D19:P19) -> 0
A20: 16 | C20: CEMENT SHOP | Q20: =SUM(D20:P20) -> 0
... A22: 18 | C22: CH-96 | Q22: =SUM(D22:P22) -> 0
A23: 19 | B23: กรรมการ | C23: CH-Exp | Q23: =SUM(D23:P23) -> 0
A24: 20 | C24: CH-Loan | Q24: =SUM(D24:P24) -> 0
A25: 21 | C25: D.N. | Q25: =SUM(D25:P25) -> 0
A26: 22 | C26: DAW YU ส่วนตัว | Q26: =SUM(D26:P26) -> 0
A27: 23 | C27: D-SHOP | Q27: =SUM(D27:P27) -> 0
A28: 24 | C28: EXP C-PAC | Q28: =SUM(D28:P28) -> 0
A29: 25 | C29: Exp KPS | Q29: =SUM(D29:P29) -> 0
A30: 26 | B30: โรงงานมะริด | C30: Exp M-SHOP | Q30: =SUM(D30:P30) -> 0
A31: 27 | C31: Exp MYEIK | Q31: =SUM(D31:P31) -> 0
A32: 28 | C32: Exp RGT | Q32: =SUM(D32:P32) -> 0
A33: 29 | C33: Exp T&Y | Q33: =SUM(D33:P33) -> 0
A34: 30 | C34: Exp RN | Q34: =SUM(D34:P34) -> 0
A35: 31 | C35: Exp VN | Q35: =SUM(D35:P35) -> 0
A36: 32 | C36: EXP VN-14 | Q36: =SUM(D36:P36) -> 0
A37: 33 | C37: Exp แพออ | Q37: =SUM(D37:P37) -> 0
A38: 34 | C38: Fish Market Fee King Star(โกคุ้ยแหง่) | Q38: =SUM(D38:P38) -> 0
A39: 35 | C39: FM | Q39: =SUM(D39:P39) -> 0
A40: 36 | C40: HHT-ICE | Q40: =SUM(D40:P40) -> 0
A41: 37 | C41: HHT IMP-EXP(A- BANK) | Q41: =SUM(D41:P41) -> 0
A42: 38 | C42: HHT IMP-EXP(AYA- BANK) | Q42: =SUM(D42:P42) -> 0
... A44: 40 | C44: HHT IMP-EXP(YOMA- BANK) | Q44: =SUM(D44:P44) -> 0
A45: 41 | B45: อวนดำ | C45: HHT-11 | Q45: =SUM(D45:P45) -> 0
A46: 42 | B46: อวนดำ | C46: HHT-12 | Q46: =SUM(D46:P46) -> 0
A47: 43 | B47: อวนดำ | C47: HHT-14 | Q47: =SUM(D47:P47) -> 0
A48: 44 | B48: อวนดำ | C48: HHT-15 | Q48: =SUM(D48:P48) -> 0
C49: HHT-16
A50: 45 | B50: อวนดำ | C50: HHT-17 | Q50: =SUM(D50:P50) -> 0
A51: 46 | B51: อวนดำ | C51: HHT-19 | Q51: =SUM(D51:P51) -> 0
C52: HHT-5
A53: 47 | C53: HHT-8 | Q53: =SUM(D53:P53) -> 0
A54: 48 | B54: กรรมการ | C54: ICE KAWTHAUNG | Q54: =SUM(D54:P54) -> 0
A55: 49 | C55: JCS MACLANIC | Q55: =SUM(D55:P55) -> 0
A56: 50 | C56: JETTY PPT | Q56: =SUM(D56:P56) -> 0
A57: 51 | C57: JETTY SM | Q57: =SUM(D57:P57) -> 0
A58: 52 | C58: K 1024-5 (KPS) | Q58: =SUM(D58:P58) -> 0
A59: 53 | C59: K 2981-1 | Q59: =SUM(D59:P59) -> 0
A60: 54 | C60: K 3138-2 (T&Y) | Q60: =SUM(D60:P60) -> 0
A61: 55 | C61: K 3395-9 (KPS) | Q61: =SUM(D61:P61) -> 0
A62: 56 | C62: K 675-3 | Q62: =SUM(D62:P62) -> 0
A63: 57 | C63: K 8311-5(K.อดิศักดิ์&K.กิตติพงษ์) | Q63: =SUM(D63:P63) -> 0
A64: 58 | C64: KF-1 | Q64: =SUM(D64:P64) -> 0
A65: 59 | C65: KLS-ค่าทัวร์อวนลาก | Q65: =SUM(D65:P65) -> 0
C66: Ko Aung Myo
A67: 60 | C67: Ko Latt | Q67: =SUM(D67:P67) -> 0
A68: 61 | C68: Ko Soe Wee*Salary | Q68: =SUM(D68:P68) -> 0
A69: 62 | B69: กรรมการ | C69: Ko Soe Wee/โกซาฮุ่ยส่วนตัว | Q69: =SUM(D69:P69) -> 0
A70: 63 | C70: Ko Than Win(z) | Q70: =SUM(D70:P70) -> 0
A71: 64 | C71: KOH LUKKY | Q71: =SUM(D71:P71) -> 0
A72: 65 | B72: ร้านค้า | C72: KPS-คอนกรีต | Q72: =SUM(D72:P72) -> 0
A73: 66 | B73: กรรมการ | C73: KPS-ท่าเรือเขานางหงส์ | Q73: =SUM(D73:P73) -> 0
A74: 67 | C74: KPS-สตีล | Q74: =SUM(D74:P74) -> 0
C75: KPS-ห้องเย็น
A76: 68 | C76: KS204 | Q76: =SUM(D76:P76) -> 0
C77: KS207
A78: 69 | B78: กรรมการ | C78: KSส่วนตัว (โกตาต้า) | Q78: =SUM(D78:P78) -> 0
A79: 70 | C79: KWB-Exp | Q79: =SUM(D79:P79) -> 0
A80: 71 | B80: ค่าปลาเรือนอก | C80: LB | Q80: =SUM(D80:P80) -> 0
A81: 72 | B81: ค่าปลาเรือนอก | C81: LB-14 | Q81: =SUM(D81:P81) -> 0
C82: Lucky-UTK
A83: 73 | C83: LYA-METAL SHEET | Q83: =SUM(D83:P83) -> 0
C84: Maung Maung Aung - Diesel
A85: 74 | C85: MIN OO(ค่าของ) | Q85: =SUM(D85:P85) -> 0
A86: 75 | C86: MIN OO(รวม) | Q86: =SUM(D86:P86) -> 0
A87: 76 | B87: ร้านค้า | C87: Mr.Decha/Engineer(ช่างเพชร) | Q87: =SUM(D87:P87) -> 0
A88: 77 | B88: โรงงานมะริด | C88: M-SHOP | Q88: =SUM(D88:P88) -> 0
C89: M-SHOP ค่าของ
A90: 78 | C90: M-Tools | Q90: =SUM(D90:P90) -> 0
A91: 79 | C91: MV.THA MIE HLA | Q91: =SUM(D91:P91) -> 0
A92: 80 | C92: ND-1 | Q92: =SUM(D92:P92) -> 0
C93: ND-5 | Q93: =SUM(D93:P93) -> 0
C94: New Boat HHT-20 | Q94: =SUM(D94:P94) -> 0
C95: New Boat HHT-999 | Q95: =SUM(D95:P95) -> 0
A96: 81 | C96: New Boat KN.22 | Q96: =SUM(D96:P96) -> 0
C97: New Boat LB-6 | Q97: =SUM(D97:P97) -> 0
A98: 82 | C98: New Boat Min Oo-5 | Q98: =SUM(D98:P98) -> 0
C99: New Boat โกต้งเรือน้ำมัน | Q99: =SUM(D99:P99) -> 0
C100: New Boat เรือน้ำมันบริษัท | Q100: =SUM(D100:P100) -> 0
A101: 83 | C101: NZY-ค่าทัวร์ | Q101: =SUM(D101:P101) -> 0
A102: 84 | C102: OFF | Q102: =SUM(D102:P102) -> 0
...

Sheet บัญชีโอน
A1: ลำดับ | B1: ชื่อร้าน | C1: จ่ายให้ | D1: BANK | E1: เลขที่บัญชี | F1: ประเภท | G1: รายละเอียด | H1: LINE
B2: AIA | C2: บจ.เอไอเอ | D2: QR CODE | E2: บจ.เอไอเอ
B3: BBL 1644-3 | C3: นายธนู ทักษิณาวงศ์ | D3: BBL | E3: 527-3-01644-3
B4: BBL 1765-6 | C4: นายอดิศักดิ์ รุจิวิวัฒนกุล | D4: BBL | E4: 527-3-01765-6
B5: BBL 5889-9 | C5: นายธนู ทักษิณาวงศ์ | D5: BBL | E5: 527-0-25889-9
B6: CHO CHO WIN | C6: CHO CHO WIN | D6: Kbank | E6: 085-8-66544-2 | F6: UST | H6: พี่เล็ก
A7: 18 | B7: GHP หนุ่มกระจกอลูมิเนียม | C7: นายยิ่งยศ แก้ววงค์ทอง | D7: BBL | E7: 527-3-01122-0 | F7: ร้านค้า | H7: หนุ่มกระจก
A8: 18 | B8: GHP หนุ่มกระจกอลูมิเนียม | C8: นายยิ่งยศ แก้ววงค์ทอง | D8: Kbank | E8: 032-3-56364-0 | F8: ร้านค้า | H8: หนุ่มกระจก
B9: K.K. Ranong Trading LTD.,PART. | C9: K.K. Ranong Trading LTD.,PART. | D9: Kbank | E9: 232-2-18817-2 | F9: UST | H9: จี้ตะซิน
B10: KS.เทรดดิ้ง | C10: นายเกรียงศักดิ์ แซ่โง้ว | D10: BBL | E10: 128-0-74064-6 | F10: ท่าเรือ | H10: ท่าเรือ
A11: 25 | B11: LYA (พี่เสง) | C11: นายปิยวุฒิ ลิ่มศิลา | D11: TTB | E11: 429-2-25632-0 | F11: ร้านค้า | H11: พี่เสง
B12: MISS GLORIA HUANG | C12: MISS GLORIA HUANG | D12: SCB | E12: 218-2-84081-5 | H12: พี่เล็ก
B13: MISS HSU MYAT HTOO | C13: MISS HSU MYAT HTOO | D13: BAY | E13: 769-1-26336-4
B14: MR. ARKER SOE THEIN | C14: MR. ARKER SOE THEIN | D14: BBL | E14: 037-4-14587-8 | F14: UST | G14: ค่าเทอมลูกชาย | H14: พี่เล็ก
B15: MR. HTAY WIN | C15: MR. HTAY WIN | D15: BBL | E15: 291-0-91259-7 | G15: โรงแรมแกรนด์อันดามัน | H15: โกจุ่ง
B16: MR. KAUNG KYAW MOE | C16: MR. KAUNG KYAW MOE | D16: Kbank | E16: 165-3-16118-9 | F16: ท่าเรือ | H16: ท่าเรือ
B17: MR. KYAW THUYA | C17: MR. KYAW THUYA | D17: BBL | E17: 527-0-24979-9 | F17: GP-ค่าของ | H17: พี่เล็ก
B18: MR. NAING LYNN | C18: MR. NAING LYNN | D18: BBL | E18: 101-9-38598-6 | G18: ค่าปลาฝากขาย | H18: พี่เล็ก
B19: MR. ZAY YAR OO | C19: MR. ZAY YAR OO | D19: Kbank | E19: 106-1-55122-7 | F19: Yส่วนตัว | H19: พี่เล็ก
B20: MR.HEIN THWE ZONE | C20: HEIN THWE ZONE | D20: BBL | E20: 855-0-83084-1 | F20: กลุ่มน้ำมัน | G20: ค่าเจ้าท่าของพม่านำเข้าน้ำมัน | H20: จี้ตะซิน/พี่เล็ก
B21: MR.SOE THEIN | C21: MR.SOE THEIN | D21: BBL | E21: 939-0-28685-5 | F21: UST
B22: MR.SUNTAYA SETAVORAPHAN | C22: MR.SUNTAYA SETAVORAPHAN | D22: BBL | E22: 180-4-97992-8 | F22: ท่าเรือ | H22: ท่าเรือ
B23: MR.THAUNG TUN | C23: MR.THAUNG TUN | D23: Kbank | E23: 140-8-79416-8 | F23: UST
B24: MR.THU KHA AND MRS.AYE AYE MU | C24: MR.THU KHA AND MRS.AYE AYE MU | D24: BBL | E24: 056-0-47678-0 | F24: โกพกส่วนตัว | H24: พี่เล็ก
B25: MR.THUYA AUNG NO SERNAME | C25: MR.THUYA AUNG NO SERNAME | D25: Kbank | E25: 550-2-04642-1 | G25: ค่า% เรืออวนดำ
B26: MR.TIN SOE | C26: MR.TIN SOE | D26: Kbank | E26: 038-3-60121-5 | G26: ค่า Agent ASIAN DAWN CO.,LTD | H26: พี่เล็ก
B27: MR.ZAW MYO TUN | C27: MR.ZAW MYO TUN | D27: BBL | E27: 031-7-11072-4 | F27: KSส่วนตัว | H27: พี่เล็ก
B28: MRS.AYE AYE MU | C28: MRS.AYE AYE MU | D28: BBL | E28: 101-9-36080-7 | F28: SM-ขายปลา | H28: พี่เล็ก
B29: MRS.KHIN HTWE KYI | C29: MRS.KHIN HTWE KYI | D29: BBL | E29: 056-0-47780-4 | F29: โกหัวส่วนตัว | H29: น้าเบิ้ล
B30: MRS.MA AYE NWAY NWAY CHAW | C30: MRS.MA AYE NWAY NWAY CHAW | D30: BBL | E30: 056-0-43520-8 | F30: โกฮุ้ยส่วนตัว | H30: น้าเบิ้ล
B31: MS.MYAT NOE THU | C31: MS.MYAT NOE THU | D31: QR CODE | E31: MS.MYAT NOE THU | F31: Ko Soe Wee/โกซาฮุ่ยส่วนตัว | H31: พี่เล็ก
B32: MS.NAN MI MI KHAING | C32: MS.NAN MI MI KHAING | D32: Kbank | E32: 004-8-95102-3 | F32: ค่าใช้จ่ายเจ้าหน้าที่เฉลี่ย | H32: พี่เล็ก
B33: MS.YIN YIN HTIKE | C33: MS.YIN YIN HTIKE | D33: BBL | E33: 031-7-11073-2 | F33: KSส่วนตัว | H33: จี้ตะซิน
B34: MS.ZIN THU HAN | C34: MS.ZIN THU HAN | D34: P-Pay | E34: 093-XXX-8262 | F34: Exp MYEIK | H34: พี่เล็ก
B35: NT Com | C35: นายนครชัย ทองอนันต์ | D35: QR CODE | E35: นายนครชัย ทองอนันต์ | F35: OFF | G35: อุปกรณ์คอมฯ (ผ่านช่างประพล) | H35: NT Com
A36: 40 | B36: PJ | C36: นายวิโรจน์ จันทปัญญา | D36: Kbank | E36: 016-8-35381-2 | F36: ร้านค้า | H36: PJ - ranong
A37: 49 | B37: PPไฮดรอลิค | C37: นายอัศวกรณ์ มิลินจารุภารัตน์ | D37: Kbank | E37: 098-1-73347-9 | F37: ร้านค้า | H37: ต้อม T.L.ไฮดรอลิค
B38: Pronpimon Oangsuwan | C38: Pronpimon Oangsuwan | D38: Kbank | E38: 138-8-42844-5 | F38: FM | G38: เงินเดือน ELDA | H38: พี่เล็ก
B39: RAM | C39: น.ส.เมธ์วดี รุจิวิวัฒนกุล | D39: KTB | E39: 806-0-43357-1 | F39: โกต้งส่วนตัว | H39: จี้เมธ์
B40: RAM(ตะแกรงไวท์เมช) | C40: น.ส.ธนาภรณ์ รุจิวิวัฒนกุล | D40: TTB | E40: 928-2-03501-4 | F40: โกต้งส่วนตัว | G40: รั้วตะแกรงไวท์เมช | H40: จี้เมธ์
B41: Ranong Hot Spring Run | C41: Ranong Hot Spring Run | D41: KTB | E41: 806-0-70823-6 | F41: KPS-ท่าเรือ | G41: บริจาคเงินงานวิ่ง | H41: อะแด้
B42: Ranong Hot Spring Run | C42: Ranong Hot Spring Run โดย | D42: KTB | E42: 806-0-79112-5 | F42: KPS-ท่าเรือ | G42: บริจาคเงินงานวิ่ง | H42: อะแด้
A43: 20 | B43: RFD / SYM | C43: บจ.ระนอง ฟิวเจอร์ ดีเวลลอปเม้นท์ | D43: BBL | E43: 527-0-22737-3 | F43: ร้านค้า | H43: โกวอม
B44: RILON | C44: คุณปณภัทร นุชเกษม | D44: KTB | E44: 493-0-21217-0 | F44: ท่าเรือ | H44: ท่าเรือ
B45: SCG Inernational Corporation Co.,Ltd | C45: SCG Inernational Corporation Co.,Ltd | D45: Kbank | E45: 020-1-00066-1 | F45: ท่าเรือ | H45: ท่าเรือ
B46: Shopeepay | C46: Shopeepay | D46: QRCode | E46: QRCode | H46: พี่เล็ก
B47: THAI KOBELCO WELDING | C47: THAI KOBELCO WELDING CO.,LTD. | D47: MIZUHO | E47: 10-764-000303 | F47: ท่าเรือ | H47: ท่าเรือ
B48: THAI-KOBELCO WELDING | C48: THAI-KOBELCO WELDING CO.,LTD. | D48: BBL | E48: 155-4-89786-6 | F48: ท่าเรือ | H48: ท่าเรือ
B49: Thongchai Sae Sae | C49: Thongchai Sae Sae | D49: SCB | E49: 140-2-18444-8 | F49: เงินโอนจี้แดง
A50: 49 | B50: TLไฮดรอลิค | C50: นายอัศวกรณ์ มิลินจารุภารัตน์ | D50: Kbank | E50: 098-1-73347-9 | F50: ร้านค้า | H50: ต้อม T.L.ไฮดรอลิค | I50: เปลี่ยนชื่อจาก TLเป็นPP(UPDATE 20/11/66)
B51: TOT | C51: บมจ.โทรคมนาคมแห่งชาติ | D51: QRCode | E51: QRCode | F51: OFF
B52: TRUE ONLINE | C52: TRUE ONLINE | D52: TRUE | E52: 23777714 | F52: OFF | G52: จ่ายภายในวันที่ 25 ของทุกเดือน
A53: 16 | B53: W.S.เซอร์วิส | C53: W.S.เซอร์วิส โดย น.ส.วาสนา รอดบุญเกิด | D53: Kbank | E53: 460-2-03111-5 | F53: ร้านค้า | H53: WS Kung
A54: 16 | B54: W.S.เซอร์วิส | C54: W.S.เซอร์วิส | D54: KTB | E54: 806-0-09277-4 | F54: ร้านค้า | H54: WS Kung | I54: Update27/2/68
B55: Wannee Kunaviriyasiri | C55: Wannee Kunaviriyasiri | D55: KTB | E55: 156-1-05507-7 | F55: KSส่วนตัว
B56: YNTZ-CPAC | C56: น.ส.สุภาพร ลิ่มศิลา | D56: Kbank | E56: 232-2-42469-0 | F56: เงินเดือนเส็ง | G56: เงินเดือนเส็ง | H56: พี่เสง
B57: ก.แสงทอง | C57: นายธนพงษ์ วรศิริสุวิมล | D57: SCB | E57: 333-2-58935-4 | F57: ค่าบรรทุกปลาป่น | H57: โกต่อ
B58: ก.แสงทอง | C58: นายธนพงษ์ วรศิริสุวิมล | D58: Kbank | E58: 037-8-45529-4 | F58: ค่าบรรทุกปลาป่น | H58: โกต่อ
B59: กรมสรรพากร | C59: กรมสรรพากร | D59: QRCode | E59: QRCode
B60: กฤษฎาค้าเหล็ก | C60: คุณอรุณพงศ์ ก้องวัชรพงศ์ | D60: Kbank | E60: 460-2-09528-8 | F60: ท่าเรือ | H60: ท่าเรือ
B61: การไฟฟ้าส่วนภูมิภาคจ.ระนอง | C61: การไฟฟ้าส่วนภูมิภาคจ.ระนอง | D61: KTB | E61: 806-1-06520-7 | H61: โกวอม
A62: 70 | B62: กิจทวีผล | C62: นางอังคณา ธีรรัตนางกูร | D62: Kbank | E62: 116-3-56620-2 | F62: ร้านค้า | H62: พี่เล็ก
A63: 22 | B63: กิจไพศาลคอนสตรัคชั่นฯ TTB | C63: บจ.กิจไพศาลคอนสตรัคชั่นแมททีเรียล | D63: TTB | E63: 429-2-41109-9 | F63: ร้านค้า | G63: ค่าคอนกรีต | H63: โกวอม&บัญชี
A64: 22 | B64: กิจไพศาลวัสดุ | C64: กิจไพศาลวัสดุ | D64: BBL | E64: 527-0-23289-4 | F64: ร้านค้า | G64: ค่าของที่ร้าน(บุคคล) | H64: โกวอม&บัญชี
A65: 22 | B65: กิจไพศาลวัสดุ | C65: นายพัชระ รุจิวิวัฒนกุล | D65: TTB | E65: 429-2-35062-8 | F65: ร้านค้า | H65: โกวอม&บัญชี
A66: 22 | B66: กิจไพศาลวัสดุ | C66: นายพัชระ รุจิวิวัฒนกุล และ นางปริยากร รุจิวิวัฒนกุล | D66: Kbank | E66: 208-3-67523-6 | F66: ร้านค้า | H66: โกวอม&บัญชี
A67: 21 | B67: กิจไพศาลวัสดุ(ด่านชั่ง) | C67: ด.ญ.นรินทร์พร รุจิวิวัฒนกุล | D67: KTB | E67: 361-0-26780-1 | F67: ร้านค้า | G67: ค่าด่านชั่งปลาป่น# / | H67: โกวอม
A68: 27 | B68: กิตตินันท์ค้าของเก่า | C68: นายนู เทียนอำไพ | D68: Kbank | E68: 460-2-07971-1 | F68: ร้านค้า | G68: ลูกกลิ้งไฟเบอร์หุ้มแสตนเลส | H68: น้าเปี๊ยก
B69: กิ๊ฟ | C69: น.ส.ธนาภรณ์ รุจิวิวัฒนกุล | D69: BBL | E69: 783-0-04515-4
B70: กิ๊ฟ | C70: น.ส.ธนาภรณ์ รุจิวิวัฒนกุล | D70: TTB | E70: 021-7-43342-4
B71: กิ๊ฟ(ตู๋) | C71: น.ส.คนึงนิจ แสงสาคร | D71: Kbank | E71: 691-2-03871-6 | G71: บัญชีส่วนตัว | H71: ตู๋
B72: โกจุ่ง | C72: นายวรากร จุลเสนีย์ชร | D72: BBL | E72: 527-0-07575-6 | F72: Staff | H72: โกจุ่ง
B73: โกจุ่ง (SM) | C73: นายวรากร จุลเสนีย์ชร | D73: BBL | E73: 527-0-27008-4 | F73: Staff | G73: เงินโอนSM | H73: โกจุ่ง
B74: โกจุ่ง (โอนต่างประเทศ) | C74: นายวรากร จุลเสนีย์ชร | D74: BBL | E74: 527-0-25450-0 | F74: Staff | G74: โอนINVโกซาหม่าว | H74: โกจุ่ง
B75: โกเจี้ยว | C75: นายนรเศรษฐ ลิ่มศิลา | D75: Kbank | E75: 460-2-02970-6 | F75: กรรมการ | G75: เงินเดือนโกเจี้ยวและครอบครัว .) | H75: โกเจี้ยว
B76: โกช้วน | C76: นายสัมพันธ์ ลิ่มศิลา | D76: Kbank | E76: 039-8-06351-1 | H76: โกจุ่ง
B77: โกช่อง(BBL) | C77: นายธนู ทักษิณาวงศ์ | D77: BBL | E77: 527-0-02422-6 | F77: กรรมการ | H77: โกช่อง
B78: โกช่อง(KBank) | C78: นายธนู ทักษิณาวงศ์ | D78: Kbank | E78: 460-2-00433-9 | F78: กรรมการ | H78: โกช่อง
B79: โกช่อง(SCB) | C79: นายธนู ทักษิณาวงศ์ (บัญชีซื้อ$) | D79: SCB | E79: 581-2-36413-7 | F79: กรรมการ | G79: โอนเงินซื้อUSD | H79: พี่เล็ก
B80: โกชุ้น | C80: นายพิเชษฐ รุจิวิวัฒนกุล | D80: Kbank | E80: 460-2-01397-4 | G80: ค่าปลา(แพจี้หง่อ) | H80: พี่เล็ก
B81: โกชุ้น (ขนส่ง) | C81: นายมนตรี อิสริยะวาณิช | D81: Kbank | E81: 232-2-21346-0 | F81: ค่าบรรทุกปลาป่น | H81: 081-892-2679
B82: โกดังสมบัติ | C82: คุณธีราภรณ์ พรชัยเจริญ | D82: Kbank | E82: 232-2-31021-0 | F82: กับข้าวลูกน้อง | G82: ค่าของแห้ง | H82: พี่ก้อง
B83: โกแดง | C83: นายธีรวัฒน์ สมแก้ว | D83: KTB | E83: 361-0-08851-6 | F83: ท่าเรือ | H83: ท่าเรือ
B84: โกแดง | C84: นายธีรวัฒน์ สมแก้ว | D84: Kbank | E84: 460-2-03450-5 | F84: ท่าเรือ | G84: โกแดง | H84: ท่าเรือ
B85: โกต้ง | C85: นายอดิศักดิ์ รุจิวิวัฒนกุล | D85: Kbank | E85: 460-2-01535-7 | F85: โกต้ง
B86: โกต้ง | C86: นายอดิศักดิ์ รุจิวิวัฒนกุล | D86: Kbank | E86: 460-1-00333-9 | H86: จี้เมธ์
B87: โกต้ง (บัญชีส่วนตัว) | C87: นายอดิศักดิ์ รุจิวิวัฒนกุล | D87: Kbank | E87: 220-1-11296-9 | H87: โกต้ง
B88: โกต้ง เพื่อ ธนาภรณ์ | C88: นายอดิศักดิ์ รุจิวิวัฒนกุลเพื่อด.ญ.ธนาภรณ์ | D88: Kbank | E88: 460-2-02025-3 | F88: โกต้ง
B89: โกนัย(ขนส่ง) | C89: น.ส.ธานิยา สอนเสริม | D89: SCB | E89: 533-2-26880-3 | F89: ค่าบรรทุกปลาป่น
B90: โกนิว | C90: นายกิตติพัฒน์ ทองสนิท | D90: BBL | E90: 527-0-10105-7 | H90: โกนิว
B91: โกปั้ง | C91: คุณอักษร วัฒนกิจ | D91: Kbank | E91: 259-2-17485-8 | F91: กรรมการ
A92: 41 | B92: โกพันธ์ | C92: นายสุรพันธุ์ อีงประเสริฐ | D92: BBL | E92: 527-0-01853-3 | F92: ร้านค้า | G92: ค่าก๊าซ | H92: โกพันธุ์
B93: โกฟุ้ก(ค่าน้ำมัน-เกาะสอง)BBL | C93: นายสง่า กังวาล | D93: BBL | E93: 291-3-05123-7
B94: โกฟุ้ก(ค่าน้ำมัน-เกาะสอง)KBank | C94: นายกานต์ กังวาล | D94: Kbank | E94: 460-1-01011-4
A95: 72 | B95: โกโรจน์ (ถัง) | C95: นายไพโรจน์ แก้วไพฑูรย์ | D95: Kbank | E95: 232-1-03997-1 | F95: ร้านค้า | G95: ถังปลา | H95: พี่เล็ก
A96: 52 | B96: โกเล็กค้าข้าว | C96: นายไพโรจน์ หนูสมตน | D96: Kbank | E96: 232-2-19808-9 | F96: ร้านค้า | G96: ข้าวมะลิกุหลาบ45กก.(65กระสอบx1,100.-) | H96: 081-535-2087
B97: โกวอม (บัญชีส่วนตัว) | C97: นายพัชระ รุจิวิวัฒนกุล | D97: KTB | E97: 361-0-15857-3 | H97: โกวอม
B98: โกวอม(บัญชีส่วนตัว) | C98: นายพัชระ รุจิวิวัฒนกุล | D98: BBL | E98: 527-0-18984-7 | F98: กรรมการ | G98: ค่าใช้จ่าย, ภาษีคืน | H98: โกวอม
B99: โกวอม(บัญชีส่วนตัว) | C99: นายพัชระ รุจิวิวัฒนกุล | D99: Kbank | E99: 460-2-70508-2 | H99: โกวอม
B100: โกหม้ก (ขนส่ง) | C100: นายมนตรี ชลิศราพงศ์ | D100: KTB | E100: 806-1-33394-5 | F100: ค่าบรรทุกปลาป่น | H100: โกหม้ก
...

Sheet ใบสำคัญจ่าย
H1: RGT | N1: M.Banking
A2: ใบสำคัญจ่าย / PAYMENT VOUCHER
N3: เลขที่ No. | O3: M69-05-003
A4: จ่ายให้ | C4: โกเจี้ยวและครอบครัว | N4: วันที่ Date | O4: =VLOOKUP(O3,'[2]5-69'!$A$3:$J$272,3,0) -> 46143
A5: Paid To
A6: จำนวนเงิน | C6: =+O14 -> 495000 | G6: ธนาคาร | H6: =VLOOKUP(C4,[3]บัญชีโอน!$B$1:$E$700,3,0) -> #N/A | I6: / | J6: =VLOOKUP(C4,[3]บัญชีโอน!$B$2:$E$700,2,0) -> #N/A | M6: / | N6: =VLOOKUP(J6,[3]บัญชีโอน!$C$1:$E$700,3,0) -> #N/A
A7: Amount | G7: Bank
A8: รหัสบัญชี | D8: ชื่อบัญชี | G8: รายการ | O8: จำนวนเงิน(บาท)
A9: A/C No. | D9: A/C | G9: Particulars | O9: Amount
D10: =VLOOKUP(O3,'[2]5-69'!$A$3:$J$272,5,0) -> โกเจี้ยวส่วนตัว | G10: =VLOOKUP(O3,'[2]5-69'!$A$3:$J$272,6,0) -> เงินเดือนโกเจี้ยวและครอบครัว 5.) | O10: =VLOOKUP(O3,'[2]5-69'!$A$3:$J$272,10,0) -> 495000
L14: รวม | O14: =SUM(O10:O13) -> 495000
L15: Total Amount
A16: จำนวนเงินเป็นตัวอักษร | F16: ="("&BAHTTEXT(O14)&")" -> (สี่แสนเก้าหมื่นห้าพันบาทถ้วน)
A17: Amount in words
A18: ผู้อนุมัติ | F18: ผู้จัดทำ | G18: GIFE | J18: ผู้ตรวจสอบ | N18: ผู้รับเงิน
A19: Authorized By | F19: Prepared By | J19: Checked By | N19: Received By
A20: วันที่ | F20: วันที่ | G20: =O4 -> 46143 | J20: วันที่ | N20: วันที่
A21: Date | F21: Date | J21: Date | N21: Date
